LXMF/Handlers.py
LXMF/LXMF.py
LXMF/LXMPeer.py
LXMF/LXMRouter.py
LXMF/LXMessage.py
LXMF/LXStamper.py
LXMF/__init__.py
LXMF/_version.py
LXMF/Utilities/lxmd.py
lxmf-0.9.3.dist-info/METADATA
lxmf-0.9.3.dist-info/WHEEL
lxmf-0.9.3.dist-info/entry_points.txt
lxmf-0.9.3.dist-info/top_level.txt
lxmf-0.9.3.dist-info/RECORD
