Metadata-Version: 2.4
Name: lxmf
Version: 0.9.3
Summary: Lightweight Extensible Message Format for Reticulum
Home-page: https://github.com/markqvist/lxmf
Author: Mark Qvist
Author-email: mark@unsigned.io
License: Reticulum License
Classifier: Programming Language :: Python :: 3
Classifier: Operating System :: OS Independent
Requires-Python: >=3.7
Requires-Dist: rns>=1.0.1
Dynamic: author
Dynamic: author-email
Dynamic: classifier
Dynamic: description
Dynamic: description-content-type
Dynamic: home-page
Dynamic: license
Dynamic: requires-dist
Dynamic: requires-python
Dynamic: summary
